pyLauda/__init__.py
pyLauda/re206.py
pyLauda/variocool.py
pyLauda-1.0.6.dist-info/LICENSE
pyLauda-1.0.6.dist-info/METADATA
pyLauda-1.0.6.dist-info/WHEEL
pyLauda-1.0.6.dist-info/top_level.txt
pyLauda-1.0.6.dist-info/RECORD
